mlscat/__init__.py
mlscat/api.py
mlscat/attacks.py
mlscat/data.py
mlscat/data_preprocess.py
mlscat/dpreprocess.py
mlscat/leakage.py
mlscat/preprocess.py
mlscat/ranks.py
mlscat/security.py
mlscat/utils.py
mlscat-0.0.9.dist-info/METADATA
mlscat-0.0.9.dist-info/WHEEL
mlscat-0.0.9.dist-info/top_level.txt
mlscat-0.0.9.dist-info/RECORD
