Metadata-Version: 2.1
Name: mlscat
Version: 0.0.9
Summary: A small cat help you enjoy your side channel attack journal!
Home-page: https://github.com/i4mhmh/mlscat
Author: i4mhmh
Author-email: i4mhmh@outlook.com
Requires-Python: >=3.8
Requires-Dist: numpy
